math_tools_fastmcp/__init__.py
math_tools_fastmcp/my_server.py
math_tools_fastmcp-0.1.0.dist-info/WHEEL
math_tools_fastmcp-0.1.0.dist-info/entry_points.txt
math_tools_fastmcp-0.1.0.dist-info/METADATA
math_tools_fastmcp-0.1.0.dist-info/RECORD
