Metadata-Version: 2.3
Name: math-tools-fastmcp
Version: 0.1.0
Summary: Add your description here
Author: tylnn68
Author-email: tylnn68 <11301536+tylnn68@user.noreply.gitee.com>
Requires-Dist: fastmcp>=2.13.0.2
Requires-Python: >=3.10
